[{"spate":["https://w3id.org/621f3"],"spat":["https://w3id.org/621f3"],"spa":["https://w3id.org/621f3"],"sp":["https://w3id.org/621f3"],"s":["https://w3id.org/621f3"],"pate":["https://w3id.org/621f3"],"pat":["https://w3id.org/621f3"],"pa":["https://w3id.org/621f3"],"p":["https://w3id.org/621f3"],"ate":["https://w3id.org/621f3"],"at":["https://w3id.org/621f3"],"a":["https://w3id.org/621f3","https://w3id.org/a20b9"],"te":["https://w3id.org/621f3"],"t":["https://w3id.org/621f3"],"e":["https://w3id.org/621f3","https://w3id.org/a20b9"],"lawnmower":["https://w3id.org/a20b9"],"lawnmowe":["https://w3id.org/a20b9"],"lawnmow":["https://w3id.org/a20b9"],"lawnmo":["https://w3id.org/a20b9"],"lawnm":["https://w3id.org/a20b9"],"lawn":["https://w3id.org/a20b9"],"law":["https://w3id.org/a20b9"],"la":["https://w3id.org/a20b9"],"l":["https://w3id.org/a20b9"],"awnmower":["https://w3id.org/a20b9"],"awnmowe":["https://w3id.org/a20b9"],"awnmow":["https://w3id.org/a20b9"],"awnmo":["https://w3id.org/a20b9"],"awnm":["https://w3id.org/a20b9"],"awn":["https://w3id.org/a20b9"],"aw":["https://w3id.org/a20b9"],"wnmower":["https://w3id.org/a20b9"],"wnmowe":["https://w3id.org/a20b9"],"wnmow":["https://w3id.org/a20b9"],"wnmo":["https://w3id.org/a20b9"],"wnm":["https://w3id.org/a20b9"],"wn":["https://w3id.org/a20b9"],"w":["https://w3id.org/a20b9"],"nmower":["https://w3id.org/a20b9"],"nmowe":["https://w3id.org/a20b9"],"nmow":["https://w3id.org/a20b9"],"nmo":["https://w3id.org/a20b9"],"nm":["https://w3id.org/a20b9"],"n":["https://w3id.org/a20b9"],"mower":["https://w3id.org/a20b9"],"mowe":["https://w3id.org/a20b9"],"mow":["https://w3id.org/a20b9"],"mo":["https://w3id.org/a20b9"],"m":["https://w3id.org/a20b9"],"ower":["https://w3id.org/a20b9"],"owe":["https://w3id.org/a20b9"],"ow":["https://w3id.org/a20b9"],"o":["https://w3id.org/a20b9"],"wer":["https://w3id.org/a20b9"],"we":["https://w3id.org/a20b9"],"er":["https://w3id.org/a20b9"],"r":["https://w3id.org/a20b9"]},{},{},{},{},{},{},{},{}]